microsoft_agents_a365/runtime/__init__.py
microsoft_agents_a365/runtime/environment_utils.py
microsoft_agents_a365/runtime/operation_error.py
microsoft_agents_a365/runtime/operation_result.py
microsoft_agents_a365/runtime/power_platform_api_discovery.py
microsoft_agents_a365/runtime/utility.py
microsoft_agents_a365/runtime/version_utils.py
microsoft_agents_a365_runtime-0.2.1.dev9.dist-info/METADATA
microsoft_agents_a365_runtime-0.2.1.dev9.dist-info/WHEEL
microsoft_agents_a365_runtime-0.2.1.dev9.dist-info/top_level.txt
microsoft_agents_a365_runtime-0.2.1.dev9.dist-info/RECORD
