Metadata-Version: 2.4
Name: microsoft-agents-a365-runtime
Version: 0.2.1.dev9
Summary: Telemetry, tracing, and monitoring components for AI agents
Author-email: Microsoft <support@microsoft.com>
License: MIT
Project-URL: Homepage, https://github.com/microsoft/Agent365-python
Project-URL: Repository, https://github.com/microsoft/Agent365-python
Project-URL: Issues, https://github.com/microsoft/Agent365-python/issues
Project-URL: Documentation, https://github.com/microsoft/Agent365-python/tree/main/libraries/microsoft-agents-a365-runtime
Keywords: observability,telemetry,tracing,opentelemetry,monitoring,ai,agents
Classifier: Development Status :: 3 - Alpha
Classifier: Intended Audience :: Developers
Classifier: Programming Language :: Python :: 3
Classifier: Programming Language :: Python :: 3.11
Classifier: Programming Language :: Python :: 3.12
Classifier: Operating System :: OS Independent
Classifier: Topic :: Software Development :: Libraries :: Python Modules
Classifier: Topic :: Scientific/Engineering :: Artificial Intelligence
Classifier: Topic :: System :: Monitoring
Requires-Python: >=3.11
Requires-Dist: PyJWT>=2.8.0
Provides-Extra: dev
Requires-Dist: pytest>=7.0.0; extra == "dev"
Requires-Dist: pytest-asyncio>=0.21.0; extra == "dev"
Requires-Dist: ruff>=0.1.0; extra == "dev"
Requires-Dist: black>=23.0.0; extra == "dev"
Requires-Dist: mypy>=1.0.0; extra == "dev"
Provides-Extra: test
Requires-Dist: pytest>=7.0.0; extra == "test"
Requires-Dist: pytest-asyncio>=0.21.0; extra == "test"
